{"v":5,"entries":{"configure-your-project--docs":{"id":"configure-your-project--docs","title":"Configure your project","name":"Docs","importPath":"./src/stories/Configure.mdx","storiesImports":[],"type":"docs","tags":["dev","test","unattached-mdx"]},"components-button--docs":{"id":"components-button--docs","title":"Components/Button","name":"Docs","importPath":"./src/stories/Button/Button.stories.ts","type":"docs","tags":["dev","test","autodocs"],"storiesImports":[]},"components-button--primary":{"type":"story","id":"components-button--primary","name":"Primary","title":"Components/Button","importPath":"./src/stories/Button/Button.stories.ts","componentPath":"./src/stories/Button/Button.tsx","tags":["dev","test","autodocs"]},"components-button--secondary":{"type":"story","id":"components-button--secondary","name":"Secondary","title":"Components/Button","importPath":"./src/stories/Button/Button.stories.ts","componentPath":"./src/stories/Button/Button.tsx","tags":["dev","test","autodocs"]},"components-button--large":{"type":"story","id":"components-button--large","name":"Large","title":"Components/Button","importPath":"./src/stories/Button/Button.stories.ts","componentPath":"./src/stories/Button/Button.tsx","tags":["dev","test","autodocs"]},"components-button--small":{"type":"story","id":"components-button--small","name":"Small","title":"Components/Button","importPath":"./src/stories/Button/Button.stories.ts","componentPath":"./src/stories/Button/Button.tsx","tags":["dev","test","autodocs"]}}}